username_cli/__init__.py
username_cli/__main__.py
username_cli/username_cli.py
username_cli-0.0.4.dist-info/METADATA
username_cli-0.0.4.dist-info/RECORD
username_cli-0.0.4.dist-info/WHEEL
username_cli-0.0.4.dist-info/entry_points.txt
username_cli-0.0.4.dist-info/top_level.txt
