Metadata-Version: 2.1
Name: username-cli
Version: 0.0.4
Summary: Get the current user name
Home-page: https://projects.abranhe.com/username-cli
Author: Carlos Abraham
Author-email: abraham@abranhe.com
License: UNKNOWN
Project-URL: Source, https://github.com/abranhe/username-cli
Platform: UNKNOWN
Classifier: Programming Language :: Python
Classifier: Natural Language :: English
Classifier: Environment :: Plugins
Classifier: Intended Audience :: Developers
Classifier: License :: OSI Approved :: MIT License
Classifier: Programming Language :: Python :: 3
Classifier: Programming Language :: Python :: 3.2
Classifier: Programming Language :: Python :: 3.3
Classifier: Programming Language :: Python :: 3.4
Requires-Dist: username
